Metadata-Version: 1.0
Name: wwspy
Version: 0.0
Summary: Work With Stroke!
Home-page: UNKNOWN
Author: UNKNOWN
Author-email: mironrobloksi@gmail.com
License: UNKNOWN
Platform: UNKNOWN
